c/Python_Vars.c
c/Python_Vars.h
c/Tensor_LocalCluster.c
c/Tensor_LocalCluster.h
c/Tensor_LpRelax.c
c/Tensor_LpRelax.h
c/Tensor_Main.c
c/Tensor_Private.c
c/Tensor_Private.h
c/Tensor_Python.c
c/UtilsOfTensor.c
c/UtilsOfTensor.h
c/default.c
c/default.h
c/sort.c
c/sort.h
nettensorpat/Default.py
nettensorpat/Funcs.py
nettensorpat/Tensor_Python.so
nettensorpat/Typing.py
nettensorpat/__init__.py
nettensorpat/wrapper.py
nettensorpat-2024.7.13.data/scripts/compile.sh
nettensorpat-2024.7.13.dist-info/METADATA
nettensorpat-2024.7.13.dist-info/WHEEL
nettensorpat-2024.7.13.dist-info/top_level.txt
nettensorpat-2024.7.13.dist-info/RECORD
