Metadata-Version: 2.1
Name: nettensorpat
Version: 2024.7.13
Summary: NetworkTensorPattern is a Python package for finding patterns in tensors.
Author-email: Paul Li <paul.shi.li.05@gmail.com>
Maintainer-email: Paul Li <paul.shi.li.05@gmail.com>
Keywords: NetworkTensorPattern,NetPat
Requires-Python: >=3.7
